roseta/__init__.py
roseta/test/__init__.py
roseta/test/age_test.py
roseta/test/city_test.py
roseta/test/cup_test.py
roseta/test/length_test.py
roseta/test/no_cls_test.py
roseta/test/transform_test.py
roseta/test/weight_test.py
roseta/transform/__init__.py
roseta/transform/age.py
roseta/transform/city.py
roseta/transform/cup.py
roseta/transform/length.py
roseta/transform/no_class.py
roseta/transform/transform.py
roseta/transform/weight.py
roseta/util/__init__.py
roseta/util/conf.py
roseta/util/data.py
roseta/util/log.py
roseta-0.1.9.dist-info/LICENSE
roseta-0.1.9.dist-info/METADATA
roseta-0.1.9.dist-info/WHEEL
roseta-0.1.9.dist-info/top_level.txt
roseta-0.1.9.dist-info/zip-safe
roseta-0.1.9.dist-info/RECORD
