Metadata-Version: 2.1
Name: roseta
Version: 0.1.9
Summary: From unstructured data to structured data.
Home-page: https://github.com/Ailln/roseta
Author: Ailln
Author-email: kinggreenhall@gmail.com
License: MIT License
Classifier: Programming Language :: Python :: 3
Classifier: Programming Language :: Python :: 3.6
Classifier: Programming Language :: Python :: 3.7
Classifier: Programming Language :: Python :: 3.8
Classifier: Programming Language :: Python :: 3.9
Classifier: License :: OSI Approved :: MIT License
Classifier: Operating System :: OS Independent
Requires-Python: >=3.6
License-File: LICENSE
Requires-Dist: setuptools (>=40.6.3)
Requires-Dist: cn2an (>=0.5.12)
Requires-Dist: proces (>=0.1.0)
